sdkit/__init__.py
sdkit/__main__.py
sdkit/filter/__init__.py
sdkit/filter/apply_filters.py
sdkit/filter/gfpgan.py
sdkit/filter/latent_upscaler.py
sdkit/filter/nsfw_checker.py
sdkit/filter/realesrgan.py
sdkit/filter/codeformer/__init__.py
sdkit/filter/codeformer/face_restoration_helper.py
sdkit/filter/codeformer/misc.py
sdkit/generate/__init__.py
sdkit/generate/image_generator.py
sdkit/generate/prompt_parser.py
sdkit/generate/sampler/__init__.py
sdkit/generate/sampler/default_samplers.py
sdkit/generate/sampler/diffusers_samplers.py
sdkit/generate/sampler/k_samplers.py
sdkit/generate/sampler/sampler_main.py
sdkit/generate/sampler/unipc_samplers/__init__.py
sdkit/generate/sampler/unipc_samplers/unipc_sampler.py
sdkit/models/__init__.py
sdkit/models/model_downloader.py
sdkit/models/scan_models.py
sdkit/models/model_loader/__init__.py
sdkit/models/model_loader/controlnet.py
sdkit/models/model_loader/controlnet_filters.py
sdkit/models/model_loader/diffusers_bugfixes.py
sdkit/models/model_loader/embeddings.py
sdkit/models/model_loader/gfpgan.py
sdkit/models/model_loader/latent_upscaler.py
sdkit/models/model_loader/lora.py
sdkit/models/model_loader/nsfw_checker.py
sdkit/models/model_loader/realesrgan.py
sdkit/models/model_loader/vae.py
sdkit/models/model_loader/codeformer/__init__.py
sdkit/models/model_loader/codeformer/codeformer_arch.py
sdkit/models/model_loader/codeformer/vqgan_arch.py
sdkit/models/model_loader/hypernetwork/__init__.py
sdkit/models/model_loader/hypernetwork/hypernetwork.py
sdkit/models/model_loader/stable_diffusion/__init__.py
sdkit/models/model_loader/stable_diffusion/accelerators.py
sdkit/models/model_loader/stable_diffusion/optimizations.py
sdkit/models/models_db/__init__.py
sdkit/models/models_db/codeformer.json
sdkit/models/models_db/controlnet.json
sdkit/models/models_db/gfpgan.json
sdkit/models/models_db/realesrgan.json
sdkit/models/models_db/stable_diffusion.json
sdkit/models/models_db/text_encoder.json
sdkit/models/models_db/vae.json
sdkit-2.1.0.dist-info/licenses/LICENSE
sdkit-2.1.0.dist-info/METADATA
sdkit-2.1.0.dist-info/WHEEL
sdkit-2.1.0.dist-info/top_level.txt
sdkit-2.1.0.dist-info/RECORD
