Metadata-Version: 2.4
Name: sdkit
Version: 2.1.0
Summary: sdkit (stable diffusion kit) is an easy-to-use library for using Stable Diffusion in your AI Art projects. It is fast, feature-packed, and memory-efficient. It bundles Stable Diffusion along with commonly-used features (like SDXL, ControlNet, LoRA, Embeddings, GFPGAN, RealESRGAN, k-samplers, custom VAE etc). It also includes a model-downloader with a database of commonly used models, and advanced features like running in parallel on multiple GPUs, auto-scanning for malicious models etc.
Author-email: cmdr2 <secondary.cmdr2@gmail.com>
Project-URL: Homepage, https://github.com/easydiffusion/sdkit
Project-URL: Bug Tracker, https://github.com/easydiffusion/sdkit/issues
Keywords: stable diffusion,ai,art
Classifier: Programming Language :: Python :: 3
Classifier: License :: OSI Approved :: MIT License
Classifier: Operating System :: Microsoft :: Windows :: Windows 10
Classifier: Operating System :: Microsoft :: Windows :: Windows 11
Classifier: Operating System :: POSIX :: Linux
Classifier: Operating System :: MacOS
Requires-Python: >=3.8.5
License-File: LICENSE
Requires-Dist: setuptools==69.5.1
Requires-Dist: stable-diffusion-sdkit==2.1.5
Requires-Dist: gfpgan
Requires-Dist: piexif
Requires-Dist: realesrgan
Requires-Dist: requests
Requires-Dist: picklescan
Requires-Dist: safetensors==0.3.3
Requires-Dist: k-diffusion==0.0.12
Requires-Dist: diffusers==0.28.2
Requires-Dist: compel==2.0.1
Requires-Dist: accelerate==0.23.0
Requires-Dist: controlnet-aux==0.0.6
Requires-Dist: invisible-watermark==0.2.0
Requires-Dist: huggingface_hub==0.21.4
Requires-Dist: torchruntime>=1.13.1
Requires-Dist: numpy<2
Dynamic: license-file
Dynamic: requires-dist
